maxframe/__init__.py
maxframe/_utils.cp312-win_amd64.pyd
maxframe/_utils.pxd
maxframe/_utils.pyi
maxframe/_utils.pyx
maxframe/conftest.py
maxframe/env.py
maxframe/errors.py
maxframe/extension.py
maxframe/mixin.py
maxframe/opcodes.py
maxframe/protocol.py
maxframe/session.py
maxframe/sperunner.py
maxframe/typing_.py
maxframe/udf.py
maxframe/utils.py
maxframe/codegen/__init__.py
maxframe/codegen/core.py
maxframe/codegen/spe/__init__.py
maxframe/codegen/spe/core.py
maxframe/codegen/spe/objects.py
maxframe/codegen/spe/remote.py
maxframe/codegen/spe/utils.py
maxframe/codegen/spe/dataframe/__init__.py
maxframe/codegen/spe/dataframe/arithmetic.py
maxframe/codegen/spe/dataframe/datasource.py
maxframe/codegen/spe/dataframe/datastore.py
maxframe/codegen/spe/dataframe/extensions.py
maxframe/codegen/spe/dataframe/fetch.py
maxframe/codegen/spe/dataframe/groupby.py
maxframe/codegen/spe/dataframe/indexing.py
maxframe/codegen/spe/dataframe/merge.py
maxframe/codegen/spe/dataframe/misc.py
maxframe/codegen/spe/dataframe/missing.py
maxframe/codegen/spe/dataframe/reduction.py
maxframe/codegen/spe/dataframe/reshape.py
maxframe/codegen/spe/dataframe/sort.py
maxframe/codegen/spe/dataframe/statistics.py
maxframe/codegen/spe/dataframe/tseries.py
maxframe/codegen/spe/dataframe/udf.py
maxframe/codegen/spe/dataframe/value_counts.py
maxframe/codegen/spe/dataframe/window.py
maxframe/codegen/spe/dataframe/accessors/__init__.py
maxframe/codegen/spe/dataframe/accessors/base.py
maxframe/codegen/spe/dataframe/accessors/dict_.py
maxframe/codegen/spe/dataframe/accessors/list_.py
maxframe/codegen/spe/dataframe/accessors/struct_.py
maxframe/codegen/spe/dataframe/tests/__init__.py
maxframe/codegen/spe/dataframe/tests/test_arithmetic.py
maxframe/codegen/spe/dataframe/tests/test_datasource.py
maxframe/codegen/spe/dataframe/tests/test_datastore.py
maxframe/codegen/spe/dataframe/tests/test_extensions.py
maxframe/codegen/spe/dataframe/tests/test_groupby.py
maxframe/codegen/spe/dataframe/tests/test_merge.py
maxframe-2.4.0.dist-info/METADATA
maxframe-2.4.0.dist-info/WHEEL
maxframe-2.4.0.dist-info/top_level.txt
maxframe-2.4.0.dist-info/RECORD
