Metadata-Version: 2.1
Name: maxframe
Version: 2.4.0
Summary: MaxFrame operator-based data analyze framework
Requires-Dist: numpy<2.0.0,>=1.19.0
Requires-Dist: pandas>=1.0.0
Requires-Dist: pyodps>=0.12.0
Requires-Dist: scipy>=1.0
Requires-Dist: pyarrow>=1.0.0
Requires-Dist: msgpack>=1.0.0
Requires-Dist: traitlets>=5.0
Requires-Dist: cloudpickle<3.0.0,>=1.5.0
Requires-Dist: pyyaml>=5.1
Requires-Dist: tornado>=6.0
Requires-Dist: defusedxml>=0.5.0
Requires-Dist: tqdm>=4.1.0
Requires-Dist: importlib-metadata>=1.4
Requires-Dist: pickle5; python_version < "3.8"
Provides-Extra: dev
Requires-Dist: black>=22.3.0; extra == "dev"
Requires-Dist: flake8>=5.0.4; extra == "dev"
Requires-Dist: flake8-type-checking>=1.0.3; extra == "dev"
Requires-Dist: pre-commit>=2.15.0; extra == "dev"
Requires-Dist: graphviz>=0.20.1; extra == "dev"
Provides-Extra: test
Requires-Dist: mock; extra == "test"
Requires-Dist: pytest>=7.3.1; extra == "test"
Requires-Dist: pytest-cov>=4.1.0; extra == "test"
Requires-Dist: pytest-asyncio>=0.21.0; extra == "test"
Requires-Dist: pytest-timeout>=2.1.0; extra == "test"
Requires-Dist: matplotlib>=2.0.0; extra == "test"
Requires-Dist: lightgbm<4.0.0,>=3.0.0; extra == "test"
Requires-Dist: scikit-learn>=1.0; extra == "test"
Requires-Dist: xgboost<2.1.0,>=1.6.2; extra == "test"
